liege/__init__.py
liege/exceptions.py
liege/liege.py
liege/models.py
liege/py.typed
liege-1.0.0.dist-info/LICENSE
liege-1.0.0.dist-info/METADATA
liege-1.0.0.dist-info/WHEEL
liege-1.0.0.dist-info/RECORD
